insteontcp/__init__.py
insteontcp/insteontcp.py
insteontcp-0.0.5.dist-info/DESCRIPTION.rst
insteontcp-0.0.5.dist-info/METADATA
insteontcp-0.0.5.dist-info/RECORD
insteontcp-0.0.5.dist-info/WHEEL
insteontcp-0.0.5.dist-info/metadata.json
insteontcp-0.0.5.dist-info/top_level.txt
