Metadata-Version: 2.0
Name: insteontcp
Version: 0.0.5
Summary: A python package that interacts with the Insteon PLMs directly over their TCP interface
Home-page: https://github.com/heathbar/insteontcp
Author: Heath Paddock
Author-email: hp@heathpaddock.com
License: MIT
Keywords: insteon,hub,tcp,plm,2012,2242-222
Platform: UNKNOWN
Classifier: Intended Audience :: Developers
Classifier: Development Status :: 3 - Alpha
Classifier: Topic :: Home Automation
Classifier: Operating System :: OS Independent
Classifier: Programming Language :: Python :: 3.4
Classifier: License :: OSI Approved :: MIT License
Requires-Dist: pyyaml (>=3.11,<4)
